LICENSE
MANIFEST.in
README.rst
mypy.ini
requirements-dev.txt
setup.cfg
setup.py
pynamodb/__init__.py
pynamodb/attributes.py
pynamodb/constants.py
pynamodb/exceptions.py
pynamodb/indexes.py
pynamodb/models.py
pynamodb/pagination.py
pynamodb/py.typed
pynamodb/settings.py
pynamodb/signals.py
pynamodb/transactions.py
pynamodb/types.py
pynamodb/util.py
pynamodb/connection/__init__.py
pynamodb/connection/base.py
pynamodb/connection/dax.py
pynamodb/connection/table.py
pynamodb/expressions/__init__.py
pynamodb/expressions/condition.py
pynamodb/expressions/operand.py
pynamodb/expressions/projection.py
pynamodb/expressions/update.py
pynamodb/expressions/util.py
pynamodb_with_dax.egg-info/PKG-INFO
pynamodb_with_dax.egg-info/SOURCES.txt
pynamodb_with_dax.egg-info/dependency_links.txt
pynamodb_with_dax.egg-info/not-zip-safe
pynamodb_with_dax.egg-info/requires.txt
pynamodb_with_dax.egg-info/top_level.txt