Metadata-Version: 2.1
Name: pynamodb-with-dax
Version: 5.3.0
Summary: A Pythonic Interface to DynamoDB
Home-page: http://jlafon.io/pynamodb.html
Author: Jharrod LaFon
Author-email: jlafon@eyesopen.com
License: MIT
Project-URL: Source, https://github.com/pynamodb/PynamoDB
Keywords: python dynamodb amazon dax
Platform: UNKNOWN
Classifier: Development Status :: 5 - Production/Stable
Classifier: Intended Audience :: Developers
Classifier: Programming Language :: Python
Classifier: Operating System :: OS Independent
Classifier: Programming Language :: Python :: 3.7
Classifier: Programming Language :: Python :: 3.8
Classifier: Programming Language :: Python :: 3.9
Classifier: Programming Language :: Python :: 3.10
Classifier: License :: OSI Approved :: MIT License
Requires-Python: >=3.7
Provides-Extra: signals
Provides-Extra: dax
License-File: LICENSE
